[
    {
        "https://www.foody.vn/siem-reap": [
            {
                "href": "https://www.foody.vn/siem-reap/costa-coffee-king-s-road-angkor",
                "src": "https://down-vn.img.susercontent.com/vn-11134259-7r98o-lwi8h0o9c99517@resize_ss640x400",
                "name": "Costa Coffee - King's Road Angkor",
                "address": "High School Rd, Siem Reab, Siem Reap",
                "user_href": "https://www.foody.vn/thanh-vien/nguyenthuhuyen.bm",
                "user_src": "https://down-vn.img.susercontent.com/vn-11134259-7r98o-lwh3f3r0cbtl32@resize_ss100x100",
                "user_name": "Nguyen Huyen",
                "user_comment": "Sang Campuchia ch\u01a1i \u0111\u01b0\u1ee3c \u00f4ng anh ch\u1edf \u0111i u\u1ed1ng cafe. C\u00f3 \u1ea3nh ch\u1ee5p \u0111\u01b0\u1ee3c c\u1ed1c cafe v\u00e0o search th\u1eed ai d\u00e8 trong foody c\u0169ng c\u00f3 qu\u00e1n lu\u00f4n m\u1edbi s\u1ee3 ch\u1ee9 :)) )). Costa Coffee l\u00e0 th\u01b0\u01a1ng hi\u1ec7u c\u00e0 ph\u00ea l\u1edbn nh\u1ea5t v\u00e0 ph\u00e1t tri\u1ec3n ...",
                "comment": "2",
                "check_in": "44"
            },
            {
                "href": "https://www.foody.vn/siem-reap/khmer-touch-cuisine-sivutha-road",
                "src": "https://down-vn.img.susercontent.com/vn-11134259-7r98o-lw9bnnviaqcbe5@resize_ss640x400",
                "name": "Khmer Touch Cuisine - Sivutha Road",
                "address": "Sivutha Road, Siem Reab, Siem Reap",
                "user_href": "https://www.foody.vn/thanh-vien/small_swallow_nyad",
                "user_src": "https://down-vn.img.susercontent.com/vn-11134259-7r98o-lwg0pknjrumx92@resize_ss100x100",
                "user_name": "Y\u1ebfn Nhi Nguy\u1ec5n",
                "user_comment": "M\u00f3n \u0103n th\u00ec n\u1ea5u r\u1ea5t ngon, ph\u1ee5c v\u1ee5 nhi\u1ec7t t\u00ecnh, ko gian sang tr\u1ecdng l\u1ecbch s\u1ef1. Tuy nhi\u00ean do gi\u00e1 h\u01a1i cao hay sao n\u00ean h\u01a1i v\u1eafng kh\u00e1ch v\u00e0o bu\u1ed5i tr\u01b0a. C\u00e1ch tr\u00ecnh b\u00e0y m\u00f3n amok ko \u0111c \u0111\u1eb9p n\u00ean h\u01a1i th\u1ea5t v\u1ecdng",
                "comment": "1",
                "check_in": "6"
            },
            {
                "href": "https://www.foody.vn/siem-reap/samapheap-restaurant",
                "src": "https://down-vn.img.susercontent.com/vn-11134259-7r98o-lwbm20txlbkpf0@resize_ss640x400",
                "name": "Samapheap Restaurant",
                "address": "N\u00b0 360, Acharsva Street, Wat Bo Village, Sala Kamroeuk Commune, Siem Reab, Siem Reap",
                "user_href": "https://www.foody.vn/thanh-vien/nachhilfe.tran",
                "user_src": "https://down-vn.img.susercontent.com/vn-11134259-7r98o-lw8t3rwltazf4d@resize_ss100x100",
                "user_name": "Tra Tran",
                "user_comment": "31.03.2016 17:00 xe d\u1eebng \u1edf Samtaphet Restaurant (S\u1ed1 360, \u0111\u01b0\u1eddng Acharsva, x\u00e3 Wat Bo, huy\u1ec7n Sala Kamroeuk, qu\u1eadn Siem Reap, t\u1ec9nh Siem Reap) g\u1ea7n Royal Residence v\u00e0 Royal Gardens. B\u00ean c\u1ea1nh nh\u00e0 h\u00e0ng l\u00e0 trung ...",
                "comment": "1",
                "check_in": "31"
            },
            {
                "href": "https://www.foody.vn/siem-reap/cambodian-cultural-village",
                "src": "https://down-vn.img.susercontent.com/vn-11134259-7r98o-lw8dxux3i28pe3@resize_ss640x400",
                "name": "Cambodian Cultural Village",
                "address": "Qu\u1ed1c L\u1ed9 6, Krong Siem Reap, Siem Reab, Siem Reap",
                "user_href": "https://www.foody.vn/thanh-vien/nachhilfe.tran",
                "user_src": "https://down-vn.img.susercontent.com/vn-11134259-7r98o-lw8t3rwltazf4d@resize_ss100x100",
                "user_name": "Tra Tran",
                "user_comment": "01.04.2016 M\u1ee5c ti\u00eau ng\u1eafm h\u1ed9t v\u1ecbt mu\u1ed1i tr\u00ean h\u1ed3 Tonle Sap coi nh\u01b0 kh\u00f4ng ho\u00e0n th\u00e0nh, v\u00ec g\u1ea7n 18:00 m\u00e0 tr\u1eddi v\u1eabn n\u1eafng chang chang. Th\u00f4i th\u00ec leo l\u00ean xe \u0111i \u0103n t\u1ed1i. L\u1ea1i \u0103n \u1edf Cambodian Cultural Village (Qu\u1ed1c ...",
                "comment": "2",
                "check_in": "101"
            },
            {
                "href": "https://www.foody.vn/siem-reap/gelato-lab-hospital-st",
                "src": "https://down-vn.img.susercontent.com/vn-11134259-7r98o-lwgnv55tx0pldc@resize_ss640x400",
                "name": "Gelato Lab - Hospital St",
                "address": "Hospital St, Siem Reab, Siem Reap",
                "user_href": "https://www.foody.vn/thanh-vien/small_swallow_nyad",
                "user_src": "https://down-vn.img.susercontent.com/vn-11134259-7r98o-lwg0pknjrumx92@resize_ss100x100",
                "user_name": "Y\u1ebfn Nhi Nguy\u1ec5n",
                "user_comment": "Y\u00eau n\u01a1i n\u00e0y v\u00ec c\u00e1ch h\u1ecd l\u00e0m \u0103n v\u00e0 kinh doanh. \u00d4ng ch\u1ee7 v\u00e0 1 s\u1ed1 nh\u00e2n vi\u00ean l\u00e0 ng\u01b0\u1eddi n\u01b0\u1edbc ngo\u00e0i, c\u00f2n l\u1ea1i l\u00e0 ng\u01b0\u1eddi b\u1ea3n \u0111\u1ecba (n\u00f3i ti\u1ebfng anh r\u1ea5t t\u1ed1t). Kem v\u00e0 sorbet \u0111\u1ec1u ngon, ch\u1eafc ko kh\u00e1c v\u1ecb th\u1eadt \u1edf \u00dd l\u00e0 m\u1ea5y. Cafe ...",
                "comment": "1",
                "check_in": "7"
            },
            {
                "href": "https://www.foody.vn/siem-reap/kaya-cafe-old-market",
                "src": "https://down-vn.img.susercontent.com/vn-11134259-7r98o-lw95i4tut8ez5e@resize_ss640x400",
                "name": "Kaya Caf\u00e9 - Old Market",
                "address": "Old Market, Siem Reab, Siem Reap",
                "user_href": "https://www.foody.vn/thanh-vien/small_swallow_nyad",
                "user_src": "https://down-vn.img.susercontent.com/vn-11134259-7r98o-lwg0pknjrumx92@resize_ss100x100",
                "user_name": "Y\u1ebfn Nhi Nguy\u1ec5n",
                "user_comment": "Qu\u00e1n n\u00e0y chuy\u00ean c\u00e1c m\u00f3n tr\u00e1ng mi\u1ec7ng Khmer tuy nhi\u00ean menu th\u00ec c\u0169ng \u0111\u1ea7y \u0111\u1ee7 nhi\u1ec1u m\u00f3n l\u1eafm. N\u00f3i chung l\u00e0 ngon h\u01a1n m\u00ecnh t\u01b0\u1edfng t\u01b0\u1ee3ng \u1edf ki\u1ec3u qu\u00e1n nh\u01b0 th\u1ebf n\u00e0y. \u0110\u1ed3 \u0103n v\u00e0 m\u1ecdi th\u1ee9 \u0111\u01b0\u1ee3c s\u1eafp x\u1ebfp v\u00e0 b\u00e0y tr\u00ed r\u1ea5t tinh ...",
                "comment": "1",
                "check_in": "18"
            }
        ]
    }
]